engineeringdoe.py
engineeringdoe-0.1.0.dist-info/LICENSE
engineeringdoe-0.1.0.dist-info/WHEEL
engineeringdoe-0.1.0.dist-info/METADATA
engineeringdoe-0.1.0.dist-info/RECORD
