Metadata-Version: 2.1
Name: engineeringdoe
Version: 0.1.0
Summary: A package for Design of Experiments (DoE) and Design Space Exploration (DSE)
Author-email: Alex Pradas <alejandro.pradas@chalmers.se>
Requires-Python: >=3.7
Classifier: License :: OSI Approved :: MIT License
Requires-Dist: pyDOE2 == 1.3
